<FlightPlan xmlns="http://aeec.aviation-ia.net/633" xmlns:xsi="http://www.w3.org/2001/XMLSchema-instance" xsi:schemaLocation="http://aeec.aviation-ia.net/633 FlightPlan.xsd" computedTime="2025-01-08T17:24:00Z" flightPlanId="10331" category="normal">
    <M633Header versionNumber="3" timestamp="2025-01-08T18:23:00Z"/>
    <M633SupplementaryHeader>
        <Flight flightOriginDate="2025-01-08" scheduledTimeOfDeparture="2025-01-08T19:33:00Z">
            <FlightIdentification>
                <FlightIdentifier>HAL203</FlightIdentifier>
                <FlightNumber airlineIATACode="HA" number="203">
                    <CommercialFlightNumber>HA203</CommercialFlightNumber>
                </FlightNumber>
            </FlightIdentification>
            <DepartureAirport airportName="DANIEL K INOUYE INTL" airportFunction="DepartureAirport">
                <AirportICAOCode>PHNL</AirportICAOCode>
                <AirportIATACode>HNL</AirportIATACode>
            </DepartureAirport>
            <ArrivalAirport airportName="LIHUE" airportFunction="ArrivalAirport">
                <AirportICAOCode>PHLI</AirportICAOCode>
                <AirportIATACode>LIH</AirportIATACode>
            </ArrivalAirport>
        </Flight>
        <Aircraft aircraftRegistration="N492HA">
            <AircraftModel airlineSpecificSubType="B717 200 BR700-715A">
                <AircraftICAOType>B712</AircraftICAOType>
            </AircraftModel>
        </Aircraft>
    </M633SupplementaryHeader>
    <FlightInfo aTCCallsign="HAL203"/>
    <Remarks>
        <Remark remarkType="ATC">
            <Paragraph><Text>(FPL-HAL203-IS
-B712/M-SDE1E2E3GIRWYZ/LB1
-PHNL1933
-N0387A140 KEOLA3 LIH DCT
-PHLI0022 PHNL
-PBN/A1B1C1D1O1S1 NAV/Z1Z2Z5P1M1 SUR/A2 DOF/250108 REG/N492HA
 SEL/LPAS OPR/HAWAIIAN AIRLINES PER/C)</Text></Paragraph>
        </Remark>
        <Remark remarkType="general">
            <Paragraph><Text>BRIEFING:
THREAT: </Text></Paragraph>
        </Remark>
        <Remark remarkType="melcdl">
            <Paragraph><Text>MEL-CDL 
M05-00-01 IN-FLIGHT ANTI-ICE CHECK
        ADMINISTRATIVE CONTROL ITEM
</Text></Paragraph>
        </Remark>
    </Remarks>
    <FlightPlanHeader>
        <AuthorInformation>
            <AuthorContact>
                <DispatchOffice>IID1</DispatchOffice>
            </AuthorContact>
        </AuthorInformation>
        <PerformanceFactor>1.020</PerformanceFactor>
        <FuelFlowInformation>
            <AverageFuelFlow>
                <Value unit="lb/h">5883</Value>
            </AverageFuelFlow>
            <HoldingFuelFlow>
                <Value unit="lb/h">4642</Value>
            </HoldingFuelFlow>
        </FuelFlowInformation>
        <RouteInformation fMSRouteName="PHNLPHLI41" routeName="R41" optimization="LC">
            <AverageWind>
                <Direction>
                    <Value unit="deg" type="true">240</Value>
                </Direction>
                <Speed>
                    <Value unit="kt">023</Value>
                </Speed>
            </AverageWind>
            <AverageWindComponent>
                <Value unit="kt">-13</Value>
            </AverageWindComponent>
            <AverageTemperature>
                <Value unit="C">1</Value>
            </AverageTemperature>
            <AverageISADeviation>
                <Value unit="C">13</Value>
            </AverageISADeviation>
            <InitialAltitude>
                <Value unit="ft/100">140</Value>
            </InitialAltitude>
            <ClimbProcedure procedure="250/308/M76"/>
            <CruiseProcedure procedure="CI040">
                <CostIndex>
                    <Value>040</Value>
                </CostIndex>
            </CruiseProcedure>
            <DescentProcedure procedure="M76/302/250"/>
            <RouteDescription>PHNL KEOLA3 LIH DCT PHLI
PHNL/FL140 </RouteDescription>
            <GroundDistance>
                <Value unit="NM">97</Value>
            </GroundDistance>
            <AirDistance>
                <Value unit="NM">100</Value>
            </AirDistance>
            <GreatCircleDistance>
                <Value unit="NM">88</Value>
            </GreatCircleDistance>
        </RouteInformation>
        <MELCDLItems>
            <MELCDLItem mELCDLType="MEL">
                <ReferenceId>05-00-01</ReferenceId>
                <Title>IN-FLIGHT ANTI-ICE CHECK
ADMINISTRATIVE CONTROL ITEM</Title>
            </MELCDLItem>
        </MELCDLItems>
    </FlightPlanHeader>
    <FuelHeader>
        <TripFuel>
            <EstimatedWeight>
                <Value unit="lb">2060</Value>
            </EstimatedWeight>
            <Duration>
                <Value>PT0H22M</Value>
            </Duration>
        </TripFuel>
        <ContingencyFuel>
            <EstimatedWeight>
                <Value unit="lb">4410</Value>
            </EstimatedWeight>
            <Duration>
                <Value>PT0H45M</Value>
            </Duration>
            <ContingencyPolicy policyName="45 MINUTES">
            </ContingencyPolicy>
        </ContingencyFuel>
        <AlternateFuels>
            <AlternateFuel>
                <EstimatedWeight>
                    <Value unit="lb">1694</Value>
                </EstimatedWeight>
                <Duration>
                    <Value>PT0H20M</Value>
                </Duration>
                <Airport airportName="DANIEL K INOUYE INTL" airportFunction="PrimaryArrivalAlternateAirport">
                    <AirportICAOCode>PHNL</AirportICAOCode>
                    <AirportIATACode>HNL</AirportIATACode>
                </Airport>
                <FinalReserve>
                    <EstimatedWeight>
                        <Value unit="lb">0</Value>
                    </EstimatedWeight>
                    <Duration>
                        <Value>PT0H0M</Value>
                    </Duration>
                </FinalReserve>
                <Sequence>1</Sequence>
            </AlternateFuel>
        </AlternateFuels>
        <AdditionalFuels>
            <AdditionalFuel reason="ATC">
                <EstimatedWeight>
                    <Value unit="lb">0</Value>
                </EstimatedWeight>
                <Duration>
                    <Value>PT00H00M</Value>
                </Duration>
            </AdditionalFuel>
            <AdditionalFuel reason="MEL CDL">
                <EstimatedWeight>
                    <Value unit="lb">0</Value>
                </EstimatedWeight>
                <Duration>
                    <Value>PT00H00M</Value>
                </Duration>
            </AdditionalFuel>
            <AdditionalFuel reason="WEATHER">
                <EstimatedWeight>
                    <Value unit="lb">0</Value>
                </EstimatedWeight>
                <Duration>
                    <Value>PT00H00M</Value>
                </Duration>
            </AdditionalFuel>
            <AdditionalFuel reason="BallastFuel">
                <EstimatedWeight>
                    <Value unit="lb">0</Value>
                </EstimatedWeight>
                <Duration>
                    <Value>PT00H00M</Value>
                </Duration>
            </AdditionalFuel>
            <AdditionalFuel reason="MinLandingFuel">
                <EstimatedWeight>
                    <Value unit="lb">0</Value>
                </EstimatedWeight>
                <Duration>
                    <Value>PT00H00M</Value>
                </Duration>
            </AdditionalFuel>
        </AdditionalFuels>
        <ExtraFuels>
            <ExtraFuel reason="DispatchDefined">
                <EstimatedWeight>
                   <Value unit="lb">0</Value>
                </EstimatedWeight>
                <Duration>
                   <Value>PT00H00M</Value>
                </Duration>
            </ExtraFuel>
            <ExtraFuel reason="EconomicTankering">
                <EstimatedWeight>
                   <Value unit="lb">0</Value>
                </EstimatedWeight>
                <Duration>
                   <Value>PT00H00M</Value>
                </Duration>
            </ExtraFuel>
            <ExtraFuel reason="Other">
                <EstimatedWeight>
                   <Value unit="lb">3196</Value>
                </EstimatedWeight>
                <Duration>
                   <Value>PT00H33M</Value>
                </Duration>
            </ExtraFuel>
        </ExtraFuels>
        <PossibleExtraFuel>
            <MaximumFuelWeight>
                <Weight>
                   <Value unit="lb">24609</Value>
                </Weight>
            </MaximumFuelWeight>
        </PossibleExtraFuel>
        <TakeOffFuel>
            <EstimatedWeight>
                <Value unit="lb">11360</Value>
           </EstimatedWeight>
           <Duration>
                <Value>PT2H0M</Value>
           </Duration>
        </TakeOffFuel>
        <TaxiFuel>
           <EstimatedWeight>
                <Value unit="lb">467</Value>
           </EstimatedWeight>
           <Duration>
                <Value>PT0H14M</Value>
           </Duration>
        </TaxiFuel>
        <BlockFuel>
           <EstimatedWeight>
                <Value unit="lb">11827</Value>
           </EstimatedWeight>
           <Duration>
                <Value>PT02H14M</Value>
           </Duration>
        </BlockFuel>
        <ArrivalFuel>
           <EstimatedWeight>
                <Value unit="lb">9300</Value>
           </EstimatedWeight>
        </ArrivalFuel>
        <Adjustments deviationReason="flight level change M1">
            <AffectedItems> 
                <Adjustment affectedItem="HighestFlightLevel" unit="ft/100">120</Adjustment>
                <Adjustment affectedItem="RouteFuelBurn" unit="lb">2088</Adjustment>
                <Adjustment affectedItem="Cost" unit="USD">1219.12</Adjustment>
                <Adjustment affectedItem="FlightTime" unit="minute">22</Adjustment>
                <Adjustment affectedItem="AverageWindComponent" unit="kt">-11</Adjustment>
                <Adjustment affectedItem="HighestTOCFlightLevel" unit="ft/100">120</Adjustment>
            </AffectedItems> 
        </Adjustments>
        <Adjustments deviationReason="flight level change M2">
            <AffectedItems> 
                <Adjustment affectedItem="HighestFlightLevel" unit="ft/100">100</Adjustment>
                <Adjustment affectedItem="RouteFuelBurn" unit="lb">2032</Adjustment>
                <Adjustment affectedItem="Cost" unit="USD">1195.39</Adjustment>
                <Adjustment affectedItem="FlightTime" unit="minute">22</Adjustment>
                <Adjustment affectedItem="AverageWindComponent" unit="kt">-9</Adjustment>
                <Adjustment affectedItem="HighestTOCFlightLevel" unit="ft/100">100</Adjustment>
            </AffectedItems> 
        </Adjustments>
        <Adjustments deviationReason="ZeroFuelWeight">
            <AffectedItems deviationReasonChange="1000" unit="lb"> 
                <Adjustment affectedItem="RouteFuelBurn" unit="lb">2073.2</Adjustment>
            </AffectedItems> 
        </Adjustments>
        <TransportCoefficientInfo>
            <IncreaseTransportCoefficient>1.01319</IncreaseTransportCoefficient>
            <DecreaseTransportCoefficient>1.01187</DecreaseTransportCoefficient>
        </TransportCoefficientInfo>
        <Remarks>
            <Remark remarkType="AcftIdleFactor">
                <Paragraph><Text>1.000</Text></Paragraph>
            </Remark>
        </Remarks>
    </FuelHeader>
    <WeightHeader>
         <DryOperatingWeight>
             <EstimatedWeight>
                 <Value unit="lb">69352</Value>
             </EstimatedWeight>
         </DryOperatingWeight>
         <Load>
             <EstimatedWeight>
                 <Value unit="lb">29148</Value>
             </EstimatedWeight>
         </Load>
         <ZeroFuelWeight>
             <EstimatedWeight>
                 <Value unit="lb">98500</Value>
             </EstimatedWeight>
             <OperationalLimit>
                 <Value unit="lb">100500</Value>
             </OperationalLimit>
             <StructuralLimit>
                 <Value unit="lb">100500</Value>
             </StructuralLimit>
         </ZeroFuelWeight>
         <TakeoffWeight>
             <EstimatedWeight>
                 <Value unit="lb">109860</Value>
             </EstimatedWeight>
             <OperationalLimit>
                 <Value unit="lb">111760</Value>
             </OperationalLimit>
             <StructuralLimit>
                 <Value unit="lb">114000</Value>
             </StructuralLimit>
         </TakeoffWeight>
         <LandingWeight>
             <EstimatedWeight>
                 <Value unit="lb">107800</Value>
             </EstimatedWeight>
             <OperationalLimit>
                 <Value unit="lb">109700</Value>
             </OperationalLimit>
             <StructuralLimit>
                 <Value unit="lb">109700</Value>
             </StructuralLimit>
         </LandingWeight>
    </WeightHeader>
    <Waypoints>
        <Waypoint waypointName="PHNL" countryICAOCode="PH" waypointId="PHNL" sequenceId="0">
            <Coordinates latitude="76746.0" longitude="-568512.0"/>
            <Airway/>
            <SegmentWind>
               <Direction>
                   <Value unit="deg" type="true">0</Value>
               </Direction>
               <Speed>
                   <Value unit="kt">0</Value>
               </Speed>
            </SegmentWind>
            <SegmentWindComponent>
               <Value unit="kt">0</Value>
            </SegmentWindComponent>
            <SegmentShearRate>
                <SegmentVerticalWindChange>
                    <Value unit="kt">0</Value>
                </SegmentVerticalWindChange>
            </SegmentShearRate>
            <SegmentTemperature>
                <Value unit="C">0</Value>
            </SegmentTemperature>
            <SegmentISADeviation>
                <Value unit="C">0</Value>
            </SegmentISADeviation>
            <Tropopause>
                <Value unit="ft/100">0</Value>
            </Tropopause>
            <TrueAirSpeed>
                <EstimatedSpeed>
                    <Value unit="kt">0</Value>
                </EstimatedSpeed>
            </TrueAirSpeed>
            <MachNumber>
                <EstimatedMachNumber>
                    <Value>0.000</Value>
                </EstimatedMachNumber>
            </MachNumber>
            <IndicatedAirSpeed>
                <EstimatedSpeed>
                    <Value unit="kt">0</Value>
                </EstimatedSpeed>
            </IndicatedAirSpeed>
            <GroundSpeed>
                <EstimatedSpeed>
                    <Value unit="kt">0</Value>
                </EstimatedSpeed>
            </GroundSpeed>
            <Tracks>
                <OutboundTrack>
                    <Value unit="deg" type="true">267.9</Value>
                </OutboundTrack>
                <OutboundTrack>
                    <Value unit="deg" type="magnetic">258.5</Value>
                </OutboundTrack>
                <SegmentTrack>
                    <Value unit="deg" type="true">0.0</Value>
                </SegmentTrack>
                <SegmentTrack>
                    <Value unit="deg" type="magnetic">0.0</Value>
                </SegmentTrack>
                <InboundTrack>
                    <Value unit="deg" type="true">0.0</Value>
                </InboundTrack>
                <InboundTrack>
                    <Value unit="deg" type="magnetic">0.0</Value>
                </InboundTrack>
            </Tracks>
            <GroundDistance>
                <Value unit="NM">0.0</Value>
            </GroundDistance>
            <RemainingGroundDistance>
                <Value unit="NM">96.9</Value>
            </RemainingGroundDistance>
            <AirDistance>
                <Value unit="NM">0.0</Value>
            </AirDistance>
            <RemainingAirDistance>
                <Value unit="NM">0100</Value>
            </RemainingAirDistance>
            <TimeFromPreviousWaypoint>
                <EstimatedTime>
                   <Value>PT00H00M</Value>
                </EstimatedTime>
            </TimeFromPreviousWaypoint>
            <TimeOverWaypoint>
                <EstimatedTime>
                    <Value>2025-01-08T19:47:00</Value>
                </EstimatedTime>
            </TimeOverWaypoint>
            <CumulatedFlightTime>
                <EstimatedTime>
                   <Value>PT00H00M</Value>
                </EstimatedTime>
            </CumulatedFlightTime>
            <RemainingFlightTime>
                <EstimatedTime>
                   <Value>PT00H22M</Value>
                </EstimatedTime>
            </RemainingFlightTime>
            <BurnOff>
                <EstimatedWeight>
                    <Value unit="lb">0</Value>
                </EstimatedWeight>
            </BurnOff>
            <CumulatedBurnOff>
                <EstimatedWeight>
                    <Value unit="lb">0</Value>
                </EstimatedWeight>
            </CumulatedBurnOff>
            <FuelOnBoard>
                <EstimatedWeight>
                    <Value unit="lb">11360</Value>
                </EstimatedWeight>
            </FuelOnBoard>
            <MinimumFuelOnBoard>
                <Value unit="lb">8164</Value>
            </MinimumFuelOnBoard>
            <Function>DepartureAirport</Function>
        </Waypoint>
        <Waypoint waypointName="TOC" waypointId="TOC" sequenceId="1">
            <Coordinates latitude="76680.0" longitude="-570342.0"/>
            <Airway>KEOLA3</Airway>
            <MinimumSafeAltitude>
                <Value unit="ft/100">35</Value>
            </MinimumSafeAltitude>
            <SegmentWind>
               <Direction>
                   <Value unit="deg" type="true">228</Value>
               </Direction>
               <Speed>
                   <Value unit="kt">12</Value>
               </Speed>
            </SegmentWind>
            <SegmentWindComponent>
               <Value unit="kt">-12</Value>
            </SegmentWindComponent>
            <SegmentShearRate>
                <SegmentVerticalWindChange>
                    <Value unit="kt">2</Value>
                </SegmentVerticalWindChange>
            </SegmentShearRate>
            <SegmentTemperature>
                <Value unit="C">10</Value>
            </SegmentTemperature>
            <SegmentISADeviation>
                <Value unit="C">10</Value>
            </SegmentISADeviation>
            <GroundSpeed>
                <EstimatedSpeed>
                    <Value unit="kt">311</Value>
                </EstimatedSpeed>
            </GroundSpeed>
            <Tracks>
                <OutboundTrack>
                    <Value unit="deg" type="true">267.8</Value>
                </OutboundTrack>
                <OutboundTrack>
                    <Value unit="deg" type="magnetic">258.3</Value>
                </OutboundTrack>
                <SegmentTrack>
                    <Value unit="deg" type="true">267.9</Value>
                </SegmentTrack>
                <SegmentTrack>
                    <Value unit="deg" type="magnetic">258.5</Value>
                </SegmentTrack>
                <InboundTrack>
                    <Value unit="deg" type="true">267.7</Value>
                </InboundTrack>
                <InboundTrack>
                    <Value unit="deg" type="magnetic">258.3</Value>
                </InboundTrack>
            </Tracks>
            <GroundDistance>
                <Value unit="NM">28.5</Value>
            </GroundDistance>
            <RemainingGroundDistance>
                <Value unit="NM">68.4</Value>
            </RemainingGroundDistance>
            <AirDistance>
                <Value unit="NM">40.4</Value>
            </AirDistance>
            <RemainingAirDistance>
                <Value unit="NM">0070</Value>
            </RemainingAirDistance>
            <TimeFromPreviousWaypoint>
                <EstimatedTime>
                   <Value>PT00H07M</Value>
                </EstimatedTime>
            </TimeFromPreviousWaypoint>
            <TimeOverWaypoint>
                <EstimatedTime>
                    <Value>2025-01-08T19:54:00</Value>
                </EstimatedTime>
            </TimeOverWaypoint>
            <CumulatedFlightTime>
                <EstimatedTime>
                   <Value>PT00H07M</Value>
                </EstimatedTime>
            </CumulatedFlightTime>
            <RemainingFlightTime>
                <EstimatedTime>
                   <Value>PT00H15M</Value>
                </EstimatedTime>
            </RemainingFlightTime>
            <BurnOff>
                <EstimatedWeight>
                    <Value unit="lb">1386</Value>
                </EstimatedWeight>
            </BurnOff>
            <CumulatedBurnOff>
                <EstimatedWeight>
                    <Value unit="lb">1386</Value>
                </EstimatedWeight>
            </CumulatedBurnOff>
            <FuelOnBoard>
                <EstimatedWeight>
                    <Value unit="lb">9974</Value>
                </EstimatedWeight>
            </FuelOnBoard>
            <MinimumFuelOnBoard>
                <Value unit="lb">6778</Value>
            </MinimumFuelOnBoard>
            <Function>TopOfClimb</Function>
        </Waypoint>
        <Waypoint waypointName="KEOLA" countryICAOCode="PH" waypointId="KEOLA" waypointLongName="KEOLA" sequenceId="2">
            <Coordinates latitude="76674.0" longitude="-570564.1"/>
            <Airway>KEOLA3</Airway>
            <Altitude>
                <EstimatedAltitude>
                    <Value unit="ft/100">140</Value>
                </EstimatedAltitude>
            </Altitude>
            <MinimumSafeAltitude>
                <Value unit="ft/100">35</Value>
            </MinimumSafeAltitude>
            <SegmentWind>
               <Direction>
                   <Value unit="deg" type="true">238</Value>
               </Direction>
               <Speed>
                   <Value unit="kt">22</Value>
               </Speed>
            </SegmentWind>
            <SegmentWindComponent>
               <Value unit="kt">-20</Value>
            </SegmentWindComponent>
            <SegmentShearRate>
                <SegmentVerticalWindChange>
                    <Value unit="kt">2</Value>
                </SegmentVerticalWindChange>
            </SegmentShearRate>
            <SegmentTemperature>
                <Value unit="C">1</Value>
            </SegmentTemperature>
            <SegmentISADeviation>
                <Value unit="C">13</Value>
            </SegmentISADeviation>
            <Tropopause>
                <Value unit="ft/100">520</Value>
            </Tropopause>
            <TrueAirSpeed>
                <EstimatedSpeed>
                    <Value unit="kt">390</Value>
                </EstimatedSpeed>
            </TrueAirSpeed>
            <MachNumber>
                <EstimatedMachNumber>
                    <Value>0.605</Value>
                </EstimatedMachNumber>
            </MachNumber>
            <IndicatedAirSpeed>
                <EstimatedSpeed>
                    <Value unit="kt">312</Value>
                </EstimatedSpeed>
            </IndicatedAirSpeed>
            <GroundSpeed>
                <EstimatedSpeed>
                    <Value unit="kt">370</Value>
                </EstimatedSpeed>
            </GroundSpeed>
            <Tracks>
                <OutboundTrack>
                    <Value unit="deg" type="true">302.2</Value>
                </OutboundTrack>
                <OutboundTrack>
                    <Value unit="deg" type="magnetic">292.7</Value>
                </OutboundTrack>
                <SegmentTrack>
                    <Value unit="deg" type="true">267.8</Value>
                </SegmentTrack>
                <SegmentTrack>
                    <Value unit="deg" type="magnetic">258.3</Value>
                </SegmentTrack>
                <InboundTrack>
                    <Value unit="deg" type="true">267.7</Value>
                </InboundTrack>
                <InboundTrack>
                    <Value unit="deg" type="magnetic">258.3</Value>
                </InboundTrack>
            </Tracks>
            <GroundDistance>
                <Value unit="NM">3.4</Value>
            </GroundDistance>
            <RemainingGroundDistance>
                <Value unit="NM">65.0</Value>
            </RemainingGroundDistance>
            <AirDistance>
                <Value unit="NM">3.6</Value>
            </AirDistance>
            <RemainingAirDistance>
                <Value unit="NM">0066</Value>
            </RemainingAirDistance>
            <TimeFromPreviousWaypoint>
                <EstimatedTime>
                   <Value>PT00H01M</Value>
                </EstimatedTime>
            </TimeFromPreviousWaypoint>
            <TimeOverWaypoint>
                <EstimatedTime>
                    <Value>2025-01-08T19:55:00</Value>
                </EstimatedTime>
            </TimeOverWaypoint>
            <CumulatedFlightTime>
                <EstimatedTime>
                   <Value>PT00H08M</Value>
                </EstimatedTime>
            </CumulatedFlightTime>
            <RemainingFlightTime>
                <EstimatedTime>
                   <Value>PT00H14M</Value>
                </EstimatedTime>
            </RemainingFlightTime>
            <BurnOff>
                <EstimatedWeight>
                    <Value unit="lb">55</Value>
                </EstimatedWeight>
            </BurnOff>
            <CumulatedBurnOff>
                <EstimatedWeight>
                    <Value unit="lb">1441</Value>
                </EstimatedWeight>
            </CumulatedBurnOff>
            <FuelOnBoard>
                <EstimatedWeight>
                    <Value unit="lb">9919</Value>
                </EstimatedWeight>
            </FuelOnBoard>
            <MinimumFuelOnBoard>
                <Value unit="lb">6723</Value>
            </MinimumFuelOnBoard>
            <Function>Enroute</Function>
        </Waypoint>
        <Waypoint waypointName="TOD" sequenceId="3">
            <Coordinates latitude="77220.0" longitude="-571500.0"/>
            <Airway>KEOLA3</Airway>
            <Altitude>
                <EstimatedAltitude>
                    <Value unit="ft/100">140</Value>
                </EstimatedAltitude>
            </Altitude>
            <MinimumSafeAltitude>
                <Value unit="ft/100">10</Value>
            </MinimumSafeAltitude>
            <SegmentWind>
               <Direction>
                   <Value unit="deg" type="true">240</Value>
               </Direction>
               <Speed>
                   <Value unit="kt">23</Value>
               </Speed>
            </SegmentWind>
            <SegmentWindComponent>
               <Value unit="kt">-11</Value>
            </SegmentWindComponent>
            <SegmentShearRate>
                <SegmentVerticalWindChange>
                    <Value unit="kt">2</Value>
                </SegmentVerticalWindChange>
            </SegmentShearRate>
            <SegmentTemperature>
                <Value unit="C">1</Value>
            </SegmentTemperature>
            <SegmentISADeviation>
                <Value unit="C">13</Value>
            </SegmentISADeviation>
            <Tropopause>
                <Value unit="ft/100">520</Value>
            </Tropopause>
            <TrueAirSpeed>
                <EstimatedSpeed>
                    <Value unit="kt">387</Value>
                </EstimatedSpeed>
            </TrueAirSpeed>
            <MachNumber>
                <EstimatedMachNumber>
                    <Value>0.600</Value>
                </EstimatedMachNumber>
            </MachNumber>
            <IndicatedAirSpeed>
                <EstimatedSpeed>
                    <Value unit="kt">309</Value>
                </EstimatedSpeed>
            </IndicatedAirSpeed>
            <GroundSpeed>
                <EstimatedSpeed>
                    <Value unit="kt">376</Value>
                </EstimatedSpeed>
            </GroundSpeed>
            <Tracks>
                <OutboundTrack>
                    <Value unit="deg" type="true">302.1</Value>
                </OutboundTrack>
                <OutboundTrack>
                    <Value unit="deg" type="magnetic">292.6</Value>
                </OutboundTrack>
                <SegmentTrack>
                    <Value unit="deg" type="true">302.2</Value>
                </SegmentTrack>
                <SegmentTrack>
                    <Value unit="deg" type="magnetic">292.7</Value>
                </SegmentTrack>
            </Tracks>
            <GroundDistance>
                <Value unit="NM">17.2</Value>
            </GroundDistance>
            <RemainingGroundDistance>
                <Value unit="NM">47.8</Value>
            </RemainingGroundDistance>
            <AirDistance>
                <Value unit="NM">17.7</Value>
            </AirDistance>
            <RemainingAirDistance>
                <Value unit="NM">0049</Value>
            </RemainingAirDistance>
            <TimeFromPreviousWaypoint>
                <EstimatedTime>
                   <Value>PT00H03M</Value>
                </EstimatedTime>
            </TimeFromPreviousWaypoint>
            <TimeOverWaypoint>
                <EstimatedTime>
                    <Value>2025-01-08T19:58:00</Value>
                </EstimatedTime>
            </TimeOverWaypoint>
            <CumulatedFlightTime>
                <EstimatedTime>
                   <Value>PT00H11M</Value>
                </EstimatedTime>
            </CumulatedFlightTime>
            <RemainingFlightTime>
                <EstimatedTime>
                   <Value>PT00H11M</Value>
                </EstimatedTime>
            </RemainingFlightTime>
            <BurnOff>
                <EstimatedWeight>
                    <Value unit="lb">269</Value>
                </EstimatedWeight>
            </BurnOff>
            <CumulatedBurnOff>
                <EstimatedWeight>
                    <Value unit="lb">1710</Value>
                </EstimatedWeight>
            </CumulatedBurnOff>
            <FuelOnBoard>
                <EstimatedWeight>
                    <Value unit="lb">9650</Value>
                </EstimatedWeight>
            </FuelOnBoard>
            <MinimumFuelOnBoard>
                <Value unit="lb">6454</Value>
            </MinimumFuelOnBoard>
            <Function>TopOfDescent</Function>
        </Waypoint>
        <Waypoint waypointName="GRAIL" countryICAOCode="PH" waypointId="GRAIL" waypointLongName="GRAIL" sequenceId="4">
            <Coordinates latitude="77448.0" longitude="-571890.0"/>
            <Airway>KEOLA3</Airway>
            <MinimumSafeAltitude>
                <Value unit="ft/100">10</Value>
            </MinimumSafeAltitude>
            <SegmentWind>
               <Direction>
                   <Value unit="deg" type="true">237</Value>
               </Direction>
               <Speed>
                   <Value unit="kt">22</Value>
               </Speed>
            </SegmentWind>
            <SegmentWindComponent>
               <Value unit="kt">-10</Value>
            </SegmentWindComponent>
            <SegmentShearRate>
                <SegmentVerticalWindChange>
                    <Value unit="kt">2</Value>
                </SegmentVerticalWindChange>
            </SegmentShearRate>
            <GroundSpeed>
                <EstimatedSpeed>
                    <Value unit="kt">363</Value>
                </EstimatedSpeed>
            </GroundSpeed>
            <Tracks>
                <OutboundTrack>
                    <Value unit="deg" type="true">302.0</Value>
                </OutboundTrack>
                <OutboundTrack>
                    <Value unit="deg" type="magnetic">292.6</Value>
                </OutboundTrack>
                <SegmentTrack>
                    <Value unit="deg" type="true">302.1</Value>
                </SegmentTrack>
                <SegmentTrack>
                    <Value unit="deg" type="magnetic">292.6</Value>
                </SegmentTrack>
                <InboundTrack>
                    <Value unit="deg" type="true">302.0</Value>
                </InboundTrack>
                <InboundTrack>
                    <Value unit="deg" type="magnetic">292.6</Value>
                </InboundTrack>
            </Tracks>
            <GroundDistance>
                <Value unit="NM">7.1</Value>
            </GroundDistance>
            <RemainingGroundDistance>
                <Value unit="NM">40.7</Value>
            </RemainingGroundDistance>
            <AirDistance>
                <Value unit="NM">7.6</Value>
            </AirDistance>
            <RemainingAirDistance>
                <Value unit="NM">0041</Value>
            </RemainingAirDistance>
            <TimeFromPreviousWaypoint>
                <EstimatedTime>
                   <Value>PT00H01M</Value>
                </EstimatedTime>
            </TimeFromPreviousWaypoint>
            <TimeOverWaypoint>
                <EstimatedTime>
                    <Value>2025-01-08T19:59:00</Value>
                </EstimatedTime>
            </TimeOverWaypoint>
            <CumulatedFlightTime>
                <EstimatedTime>
                   <Value>PT00H12M</Value>
                </EstimatedTime>
            </CumulatedFlightTime>
            <RemainingFlightTime>
                <EstimatedTime>
                   <Value>PT00H10M</Value>
                </EstimatedTime>
            </RemainingFlightTime>
            <BurnOff>
                <EstimatedWeight>
                    <Value unit="lb">22</Value>
                </EstimatedWeight>
            </BurnOff>
            <CumulatedBurnOff>
                <EstimatedWeight>
                    <Value unit="lb">1732</Value>
                </EstimatedWeight>
            </CumulatedBurnOff>
            <FuelOnBoard>
                <EstimatedWeight>
                    <Value unit="lb">9628</Value>
                </EstimatedWeight>
            </FuelOnBoard>
            <MinimumFuelOnBoard>
                <Value unit="lb">6432</Value>
            </MinimumFuelOnBoard>
            <Function>Enroute</Function>
        </Waypoint>
        <Waypoint waypointName="NAPUA" countryICAOCode="PH" waypointId="NAPUA" waypointLongName="NAPUA" sequenceId="5">
            <Coordinates latitude="78252.0" longitude="-573276.0"/>
            <Airway>KEOLA3</Airway>
            <MinimumSafeAltitude>
                <Value unit="ft/100">10</Value>
            </MinimumSafeAltitude>
            <SegmentWind>
               <Direction>
                   <Value unit="deg" type="true">227</Value>
               </Direction>
               <Speed>
                   <Value unit="kt">12</Value>
               </Speed>
            </SegmentWind>
            <SegmentWindComponent>
               <Value unit="kt">-4</Value>
            </SegmentWindComponent>
            <SegmentShearRate>
                <SegmentVerticalWindChange>
                    <Value unit="kt">3</Value>
                </SegmentVerticalWindChange>
            </SegmentShearRate>
            <GroundSpeed>
                <EstimatedSpeed>
                    <Value unit="kt">306</Value>
                </EstimatedSpeed>
            </GroundSpeed>
            <Tracks>
                <OutboundTrack>
                    <Value unit="deg" type="true">338.9</Value>
                </OutboundTrack>
                <OutboundTrack>
                    <Value unit="deg" type="magnetic">329.5</Value>
                </OutboundTrack>
                <SegmentTrack>
                    <Value unit="deg" type="true">302.0</Value>
                </SegmentTrack>
                <SegmentTrack>
                    <Value unit="deg" type="magnetic">292.6</Value>
                </SegmentTrack>
                <InboundTrack>
                    <Value unit="deg" type="true">301.9</Value>
                </InboundTrack>
                <InboundTrack>
                    <Value unit="deg" type="magnetic">292.4</Value>
                </InboundTrack>
            </Tracks>
            <GroundDistance>
                <Value unit="NM">25.3</Value>
            </GroundDistance>
            <RemainingGroundDistance>
                <Value unit="NM">15.4</Value>
            </RemainingGroundDistance>
            <AirDistance>
                <Value unit="NM">28.3</Value>
            </AirDistance>
            <RemainingAirDistance>
                <Value unit="NM">0016</Value>
            </RemainingAirDistance>
            <TimeFromPreviousWaypoint>
                <EstimatedTime>
                   <Value>PT00H06M</Value>
                </EstimatedTime>
            </TimeFromPreviousWaypoint>
            <TimeOverWaypoint>
                <EstimatedTime>
                    <Value>2025-01-08T20:05:00</Value>
                </EstimatedTime>
            </TimeOverWaypoint>
            <CumulatedFlightTime>
                <EstimatedTime>
                   <Value>PT00H18M</Value>
                </EstimatedTime>
            </CumulatedFlightTime>
            <RemainingFlightTime>
                <EstimatedTime>
                   <Value>PT00H04M</Value>
                </EstimatedTime>
            </RemainingFlightTime>
            <BurnOff>
                <EstimatedWeight>
                    <Value unit="lb">128</Value>
                </EstimatedWeight>
            </BurnOff>
            <CumulatedBurnOff>
                <EstimatedWeight>
                    <Value unit="lb">1860</Value>
                </EstimatedWeight>
            </CumulatedBurnOff>
            <FuelOnBoard>
                <EstimatedWeight>
                    <Value unit="lb">9500</Value>
                </EstimatedWeight>
            </FuelOnBoard>
            <MinimumFuelOnBoard>
                <Value unit="lb">6304</Value>
            </MinimumFuelOnBoard>
            <Function>Enroute</Function>
        </Waypoint>
        <Waypoint waypointName="LIH" countryICAOCode="PH" waypointId="LIH" waypointLongName="LIHUE" sequenceId="6">
            <Coordinates latitude="79074.0" longitude="-573618.0"/>
            <Airway>KEOLA3</Airway>
            <MinimumSafeAltitude>
                <Value unit="ft/100">59</Value>
            </MinimumSafeAltitude>
            <SegmentWind>
               <Direction>
                   <Value unit="deg" type="true">69</Value>
               </Direction>
               <Speed>
                   <Value unit="kt">7</Value>
               </Speed>
            </SegmentWind>
            <SegmentWindComponent>
               <Value unit="kt">0</Value>
            </SegmentWindComponent>
            <SegmentShearRate>
                <SegmentVerticalWindChange>
                    <Value unit="kt">4</Value>
                </SegmentVerticalWindChange>
            </SegmentShearRate>
            <GroundSpeed>
                <EstimatedSpeed>
                    <Value unit="kt">258</Value>
                </EstimatedSpeed>
            </GroundSpeed>
            <Tracks>
                <OutboundTrack>
                    <Value unit="deg" type="true">0.0</Value>
                </OutboundTrack>
                <OutboundTrack>
                    <Value unit="deg" type="magnetic">350.5</Value>
                </OutboundTrack>
                <SegmentTrack>
                    <Value unit="deg" type="true">338.9</Value>
                </SegmentTrack>
                <SegmentTrack>
                    <Value unit="deg" type="magnetic">329.5</Value>
                </SegmentTrack>
                <InboundTrack>
                    <Value unit="deg" type="true">338.9</Value>
                </InboundTrack>
                <InboundTrack>
                    <Value unit="deg" type="magnetic">329.4</Value>
                </InboundTrack>
            </Tracks>
            <GroundDistance>
                <Value unit="NM">14.7</Value>
            </GroundDistance>
            <RemainingGroundDistance>
                <Value unit="NM">0.7</Value>
            </RemainingGroundDistance>
            <AirDistance>
                <Value unit="NM">18.5</Value>
            </AirDistance>
            <RemainingAirDistance>
                <Value unit="NM">0001</Value>
            </RemainingAirDistance>
            <TimeFromPreviousWaypoint>
                <EstimatedTime>
                   <Value>PT00H04M</Value>
                </EstimatedTime>
            </TimeFromPreviousWaypoint>
            <TimeOverWaypoint>
                <EstimatedTime>
                    <Value>2025-01-08T20:09:00</Value>
                </EstimatedTime>
            </TimeOverWaypoint>
            <CumulatedFlightTime>
                <EstimatedTime>
                   <Value>PT00H22M</Value>
                </EstimatedTime>
            </CumulatedFlightTime>
            <RemainingFlightTime>
                <EstimatedTime>
                   <Value>PT00H00M</Value>
                </EstimatedTime>
            </RemainingFlightTime>
            <BurnOff>
                <EstimatedWeight>
                    <Value unit="lb">188</Value>
                </EstimatedWeight>
            </BurnOff>
            <CumulatedBurnOff>
                <EstimatedWeight>
                    <Value unit="lb">2048</Value>
                </EstimatedWeight>
            </CumulatedBurnOff>
            <FuelOnBoard>
                <EstimatedWeight>
                    <Value unit="lb">9312</Value>
                </EstimatedWeight>
            </FuelOnBoard>
            <MinimumFuelOnBoard>
                <Value unit="lb">6116</Value>
            </MinimumFuelOnBoard>
            <Remarks>
                <Remark remarkType="VOR frequency">
                    <Paragraph><Text>113.50</Text></Paragraph>
                </Remark>
            </Remarks>
            <Function>Vhf</Function>
        </Waypoint>
        <Waypoint waypointName="PHLI" countryICAOCode="PH" waypointId="PHLI" sequenceId="7">
            <Coordinates latitude="79116.0" longitude="-573618.0"/>
            <Airway>DCT</Airway>
            <MinimumSafeAltitude>
                <Value unit="ft/100">59</Value>
            </MinimumSafeAltitude>
            <SegmentWind>
               <Direction>
                   <Value unit="deg" type="true">73</Value>
               </Direction>
               <Speed>
                   <Value unit="kt">11</Value>
               </Speed>
            </SegmentWind>
            <SegmentWindComponent>
               <Value unit="kt">-4</Value>
            </SegmentWindComponent>
            <SegmentShearRate>
                <SegmentVerticalWindChange>
                    <Value unit="kt">4</Value>
                </SegmentVerticalWindChange>
            </SegmentShearRate>
            <GroundSpeed>
                <EstimatedSpeed>
                    <Value unit="kt">252</Value>
                </EstimatedSpeed>
            </GroundSpeed>
            <Tracks>
                <OutboundTrack>
                    <Value unit="deg" type="true">0.0</Value>
                </OutboundTrack>
                <OutboundTrack>
                    <Value unit="deg" type="magnetic">350.5</Value>
                </OutboundTrack>
                <SegmentTrack>
                    <Value unit="deg" type="true">0.0</Value>
                </SegmentTrack>
                <SegmentTrack>
                    <Value unit="deg" type="magnetic">350.5</Value>
                </SegmentTrack>
                <InboundTrack>
                    <Value unit="deg" type="true">0.0</Value>
                </InboundTrack>
                <InboundTrack>
                    <Value unit="deg" type="magnetic">350.5</Value>
                </InboundTrack>
            </Tracks>
            <GroundDistance>
                <Value unit="NM">0.7</Value>
            </GroundDistance>
            <RemainingGroundDistance>
                <Value unit="NM">0.0</Value>
            </RemainingGroundDistance>
            <AirDistance>
                <Value unit="NM">1.0</Value>
            </AirDistance>
            <RemainingAirDistance>
                <Value unit="NM">0000</Value>
            </RemainingAirDistance>
            <TimeFromPreviousWaypoint>
                <EstimatedTime>
                   <Value>PT00H00M</Value>
                </EstimatedTime>
            </TimeFromPreviousWaypoint>
            <TimeOverWaypoint>
                <EstimatedTime>
                    <Value>2025-01-08T20:09:00</Value>
                </EstimatedTime>
            </TimeOverWaypoint>
            <CumulatedFlightTime>
                <EstimatedTime>
                   <Value>PT00H22M</Value>
                </EstimatedTime>
            </CumulatedFlightTime>
            <RemainingFlightTime>
                <EstimatedTime>
                   <Value>PT00H00M</Value>
                </EstimatedTime>
            </RemainingFlightTime>
            <BurnOff>
                <EstimatedWeight>
                    <Value unit="lb">12</Value>
                </EstimatedWeight>
            </BurnOff>
            <CumulatedBurnOff>
                <EstimatedWeight>
                    <Value unit="lb">2060</Value>
                </EstimatedWeight>
            </CumulatedBurnOff>
            <FuelOnBoard>
                <EstimatedWeight>
                    <Value unit="lb">9300</Value>
                </EstimatedWeight>
            </FuelOnBoard>
            <MinimumFuelOnBoard>
                <Value unit="lb">6104</Value>
            </MinimumFuelOnBoard>
            <Function>ArrivalAirport</Function>
        </Waypoint>
     </Waypoints>
     <FlightPlanSummary>
         <ScheduledTimeOfArrival>2025-01-08T20:15:00Z</ScheduledTimeOfArrival>
        <OutTime>
            <EstimatedTime>
                <Value>2025-01-08T19:33:00Z</Value>
            </EstimatedTime>
        </OutTime>
        <OffTime>
            <EstimatedTime>
                <Value>2025-01-08T19:47:00Z</Value>
            </EstimatedTime>
        </OffTime>
        <OnTime>
            <EstimatedTime>
               <Value>2025-01-08T20:09:00Z</Value>
            </EstimatedTime>
        </OnTime>
        <InTime>
            <EstimatedTime>
               <Value>2025-01-08T20:15:00Z</Value>
            </EstimatedTime>
        </InTime>
        <BlockTime>
            <EstimatedTime>
                <Value>PT00H42M</Value>
            </EstimatedTime>
        </BlockTime>
        <TaxiOutTime>
            <EstimatedTime>
                <Value>PT00H14M</Value>
            </EstimatedTime>
        </TaxiOutTime>
        <FlightTime>
            <EstimatedTime>
               <Value>PT00H22M</Value>
            </EstimatedTime>
        </FlightTime>
        <TaxiInTime>
            <EstimatedTime><Value>PT00H06M</Value></EstimatedTime>
        </TaxiInTime>
     </FlightPlanSummary>
     <AlternateRoutes>
        <AlternateRoute>
            <Waypoints>
        <Waypoint waypointName="PHLI" countryICAOCode="PH" waypointId="PHLI" sequenceId="8">
            <Coordinates latitude="79116.0" longitude="-573618.0"/>
            <Airway/>
            <Altitude>
                <EstimatedAltitude>
                    <Value unit="ft/100">0</Value>
                </EstimatedAltitude>
            </Altitude>
            <MinimumSafeAltitude>
                <Value unit="ft/100">0</Value>
            </MinimumSafeAltitude>
            <SegmentWind>
               <Direction>
                   <Value unit="deg" type="true">0</Value>
               </Direction>
               <Speed>
                   <Value unit="kt">0</Value>
               </Speed>
            </SegmentWind>
            <SegmentWindComponent>
               <Value unit="kt">0</Value>
            </SegmentWindComponent>
            <SegmentShearRate>
                <SegmentVerticalWindChange>
                    <Value unit="kt">0</Value>
                </SegmentVerticalWindChange>
            </SegmentShearRate>
            <SegmentTemperature>
                <Value unit="C">0</Value>
            </SegmentTemperature>
            <SegmentISADeviation>
                <Value unit="C">0</Value>
            </SegmentISADeviation>
            <Tropopause>
                <Value unit="ft/100">0</Value>
            </Tropopause>
            <TrueAirSpeed>
                <EstimatedSpeed>
                    <Value unit="kt">0</Value>
                </EstimatedSpeed>
            </TrueAirSpeed>
            <MachNumber>
                <EstimatedMachNumber>
                    <Value>0.000</Value>
                </EstimatedMachNumber>
            </MachNumber>
            <IndicatedAirSpeed>
                <EstimatedSpeed>
                    <Value unit="kt">0</Value>
                </EstimatedSpeed>
            </IndicatedAirSpeed>
            <GroundSpeed>
                <EstimatedSpeed>
                    <Value unit="kt">0</Value>
                </EstimatedSpeed>
            </GroundSpeed>
            <Tracks>
                <OutboundTrack>
                    <Value unit="deg" type="true">180.0</Value>
                </OutboundTrack>
                <OutboundTrack>
                    <Value unit="deg" type="magnetic">170.5</Value>
                </OutboundTrack>
                <SegmentTrack>
                    <Value unit="deg" type="true">0.0</Value>
                </SegmentTrack>
                <SegmentTrack>
                    <Value unit="deg" type="magnetic">0.0</Value>
                </SegmentTrack>
                <InboundTrack>
                    <Value unit="deg" type="true">0.0</Value>
                </InboundTrack>
                <InboundTrack>
                    <Value unit="deg" type="magnetic">0.0</Value>
                </InboundTrack>
            </Tracks>
            <GroundDistance>
                <Value unit="NM">0.0</Value>
            </GroundDistance>
            <RemainingGroundDistance>
                <Value unit="NM">91.3</Value>
            </RemainingGroundDistance>
            <AirDistance>
                <Value unit="NM">0.0</Value>
            </AirDistance>
            <RemainingAirDistance>
                <Value unit="NM">0090</Value>
            </RemainingAirDistance>
            <TimeFromPreviousWaypoint>
                <EstimatedTime>
                   <Value>PT00H00M</Value>
                </EstimatedTime>
            </TimeFromPreviousWaypoint>
            <TimeOverWaypoint>
                <EstimatedTime>
                    <Value>2025-01-08T20:09:00</Value>
                </EstimatedTime>
            </TimeOverWaypoint>
            <CumulatedFlightTime>
                <EstimatedTime>
                   <Value>PT00H00M</Value>
                </EstimatedTime>
            </CumulatedFlightTime>
            <RemainingFlightTime>
                <EstimatedTime>
                   <Value>PT00H20M</Value>
                </EstimatedTime>
            </RemainingFlightTime>
            <BurnOff>
                <EstimatedWeight>
                    <Value unit="lb">0</Value>
                </EstimatedWeight>
            </BurnOff>
            <CumulatedBurnOff>
                <EstimatedWeight>
                    <Value unit="lb">0</Value>
                </EstimatedWeight>
            </CumulatedBurnOff>
            <FuelOnBoard>
                <EstimatedWeight>
                    <Value unit="lb">9300</Value>
                </EstimatedWeight>
            </FuelOnBoard>
            <MinimumFuelOnBoard>
                <Value unit="lb">6104</Value>
            </MinimumFuelOnBoard>
            <Function>ArrivalAirport</Function>
        </Waypoint>
        <Waypoint waypointName="LIH" countryICAOCode="PH" waypointId="LIH" waypointLongName="LIHUE" sequenceId="9">
            <Coordinates latitude="79074.0" longitude="-573618.0"/>
            <Airway>DCT</Airway>
            <MinimumSafeAltitude>
                <Value unit="ft/100">59</Value>
            </MinimumSafeAltitude>
            <SegmentWind>
               <Direction>
                   <Value unit="deg" type="true">73</Value>
               </Direction>
               <Speed>
                   <Value unit="kt">11</Value>
               </Speed>
            </SegmentWind>
            <SegmentWindComponent>
               <Value unit="kt">3</Value>
            </SegmentWindComponent>
            <SegmentShearRate>
                <SegmentVerticalWindChange>
                    <Value unit="kt">4</Value>
                </SegmentVerticalWindChange>
            </SegmentShearRate>
            <GroundSpeed>
                <EstimatedSpeed>
                    <Value unit="kt">258</Value>
                </EstimatedSpeed>
            </GroundSpeed>
            <Tracks>
                <OutboundTrack>
                    <Value unit="deg" type="true">121.2</Value>
                </OutboundTrack>
                <OutboundTrack>
                    <Value unit="deg" type="magnetic">111.7</Value>
                </OutboundTrack>
                <SegmentTrack>
                    <Value unit="deg" type="true">180.0</Value>
                </SegmentTrack>
                <SegmentTrack>
                    <Value unit="deg" type="magnetic">170.5</Value>
                </SegmentTrack>
                <InboundTrack>
                    <Value unit="deg" type="true">180.0</Value>
                </InboundTrack>
                <InboundTrack>
                    <Value unit="deg" type="magnetic">170.5</Value>
                </InboundTrack>
            </Tracks>
            <GroundDistance>
                <Value unit="NM">0.7</Value>
            </GroundDistance>
            <RemainingGroundDistance>
                <Value unit="NM">90.6</Value>
            </RemainingGroundDistance>
            <AirDistance>
                <Value unit="NM">0.7</Value>
            </AirDistance>
            <RemainingAirDistance>
                <Value unit="NM">0089</Value>
            </RemainingAirDistance>
            <TimeFromPreviousWaypoint>
                <EstimatedTime>
                   <Value>PT00H00M</Value>
                </EstimatedTime>
            </TimeFromPreviousWaypoint>
            <TimeOverWaypoint>
                <EstimatedTime>
                    <Value>2025-01-08T20:09:00</Value>
                </EstimatedTime>
            </TimeOverWaypoint>
            <CumulatedFlightTime>
                <EstimatedTime>
                   <Value>PT00H00M</Value>
                </EstimatedTime>
            </CumulatedFlightTime>
            <RemainingFlightTime>
                <EstimatedTime>
                   <Value>PT00H20M</Value>
                </EstimatedTime>
            </RemainingFlightTime>
            <BurnOff>
                <EstimatedWeight>
                    <Value unit="lb">37</Value>
                </EstimatedWeight>
            </BurnOff>
            <CumulatedBurnOff>
                <EstimatedWeight>
                    <Value unit="lb">37</Value>
                </EstimatedWeight>
            </CumulatedBurnOff>
            <FuelOnBoard>
                <EstimatedWeight>
                    <Value unit="lb">9263</Value>
                </EstimatedWeight>
            </FuelOnBoard>
            <MinimumFuelOnBoard>
                <Value unit="lb">6067</Value>
            </MinimumFuelOnBoard>
            <Remarks>
                <Remark remarkType="VOR frequency">
                    <Paragraph><Text>113.50</Text></Paragraph>
                </Remark>
            </Remarks>
            <Function>Vhf</Function>
        </Waypoint>
        <Waypoint waypointName="ZIKAB" countryICAOCode="PH" waypointId="ZIKAB" waypointLongName="ZIKAB" sequenceId="10">
            <Coordinates latitude="78294.0" longitude="-572232.1"/>
            <Airway>V15</Airway>
            <MinimumSafeAltitude>
                <Value unit="ft/100">59</Value>
            </MinimumSafeAltitude>
            <SegmentWind>
               <Direction>
                   <Value unit="deg" type="true">210</Value>
               </Direction>
               <Speed>
                   <Value unit="kt">10</Value>
               </Speed>
            </SegmentWind>
            <SegmentWindComponent>
               <Value unit="kt">-1</Value>
            </SegmentWindComponent>
            <SegmentShearRate>
                <SegmentVerticalWindChange>
                    <Value unit="kt">4</Value>
                </SegmentVerticalWindChange>
            </SegmentShearRate>
            <GroundSpeed>
                <EstimatedSpeed>
                    <Value unit="kt">285</Value>
                </EstimatedSpeed>
            </GroundSpeed>
            <Tracks>
                <OutboundTrack>
                    <Value unit="deg" type="true">121.2</Value>
                </OutboundTrack>
                <OutboundTrack>
                    <Value unit="deg" type="magnetic">111.8</Value>
                </OutboundTrack>
                <SegmentTrack>
                    <Value unit="deg" type="true">121.2</Value>
                </SegmentTrack>
                <SegmentTrack>
                    <Value unit="deg" type="magnetic">111.7</Value>
                </SegmentTrack>
                <InboundTrack>
                    <Value unit="deg" type="true">121.3</Value>
                </InboundTrack>
                <InboundTrack>
                    <Value unit="deg" type="magnetic">111.8</Value>
                </InboundTrack>
            </Tracks>
            <GroundDistance>
                <Value unit="NM">25.1</Value>
            </GroundDistance>
            <RemainingGroundDistance>
                <Value unit="NM">65.5</Value>
            </RemainingGroundDistance>
            <AirDistance>
                <Value unit="NM">25.2</Value>
            </AirDistance>
            <RemainingAirDistance>
                <Value unit="NM">0064</Value>
            </RemainingAirDistance>
            <TimeFromPreviousWaypoint>
                <EstimatedTime>
                   <Value>PT00H05M</Value>
                </EstimatedTime>
            </TimeFromPreviousWaypoint>
            <TimeOverWaypoint>
                <EstimatedTime>
                    <Value>2025-01-08T20:14:00</Value>
                </EstimatedTime>
            </TimeOverWaypoint>
            <CumulatedFlightTime>
                <EstimatedTime>
                   <Value>PT00H05M</Value>
                </EstimatedTime>
            </CumulatedFlightTime>
            <RemainingFlightTime>
                <EstimatedTime>
                   <Value>PT00H15M</Value>
                </EstimatedTime>
            </RemainingFlightTime>
            <BurnOff>
                <EstimatedWeight>
                    <Value unit="lb">1010</Value>
                </EstimatedWeight>
            </BurnOff>
            <CumulatedBurnOff>
                <EstimatedWeight>
                    <Value unit="lb">1047</Value>
                </EstimatedWeight>
            </CumulatedBurnOff>
            <FuelOnBoard>
                <EstimatedWeight>
                    <Value unit="lb">8253</Value>
                </EstimatedWeight>
            </FuelOnBoard>
            <MinimumFuelOnBoard>
                <Value unit="lb">5057</Value>
            </MinimumFuelOnBoard>
            <Function>Enroute</Function>
        </Waypoint>
        <Waypoint waypointName="TOC" waypointId="TOC" sequenceId="11">
            <Coordinates latitude="78204.0" longitude="-572070.0"/>
            <Airway>V15</Airway>
            <MinimumSafeAltitude>
                <Value unit="ft/100">10</Value>
            </MinimumSafeAltitude>
            <SegmentWind>
               <Direction>
                   <Value unit="deg" type="true">237</Value>
               </Direction>
               <Speed>
                   <Value unit="kt">22</Value>
               </Speed>
            </SegmentWind>
            <SegmentWindComponent>
               <Value unit="kt">10</Value>
            </SegmentWindComponent>
            <SegmentShearRate>
                <SegmentVerticalWindChange>
                    <Value unit="kt">2</Value>
                </SegmentVerticalWindChange>
            </SegmentShearRate>
            <GroundSpeed>
                <EstimatedSpeed>
                    <Value unit="kt">367</Value>
                </EstimatedSpeed>
            </GroundSpeed>
            <Tracks>
                <OutboundTrack>
                    <Value unit="deg" type="true">121.3</Value>
                </OutboundTrack>
                <OutboundTrack>
                    <Value unit="deg" type="magnetic">111.8</Value>
                </OutboundTrack>
                <SegmentTrack>
                    <Value unit="deg" type="true">121.2</Value>
                </SegmentTrack>
                <SegmentTrack>
                    <Value unit="deg" type="magnetic">111.8</Value>
                </SegmentTrack>
                <InboundTrack>
                    <Value unit="deg" type="true">121.4</Value>
                </InboundTrack>
                <InboundTrack>
                    <Value unit="deg" type="magnetic">112.0</Value>
                </InboundTrack>
            </Tracks>
            <GroundDistance>
                <Value unit="NM">3.0</Value>
            </GroundDistance>
            <RemainingGroundDistance>
                <Value unit="NM">62.5</Value>
            </RemainingGroundDistance>
            <AirDistance>
                <Value unit="NM">2.9</Value>
            </AirDistance>
            <RemainingAirDistance>
                <Value unit="NM">0061</Value>
            </RemainingAirDistance>
            <TimeFromPreviousWaypoint>
                <EstimatedTime>
                   <Value>PT00H01M</Value>
                </EstimatedTime>
            </TimeFromPreviousWaypoint>
            <TimeOverWaypoint>
                <EstimatedTime>
                    <Value>2025-01-08T20:15:00</Value>
                </EstimatedTime>
            </TimeOverWaypoint>
            <CumulatedFlightTime>
                <EstimatedTime>
                   <Value>PT00H06M</Value>
                </EstimatedTime>
            </CumulatedFlightTime>
            <RemainingFlightTime>
                <EstimatedTime>
                   <Value>PT00H14M</Value>
                </EstimatedTime>
            </RemainingFlightTime>
            <BurnOff>
                <EstimatedWeight>
                    <Value unit="lb">69</Value>
                </EstimatedWeight>
            </BurnOff>
            <CumulatedBurnOff>
                <EstimatedWeight>
                    <Value unit="lb">1116</Value>
                </EstimatedWeight>
            </CumulatedBurnOff>
            <FuelOnBoard>
                <EstimatedWeight>
                    <Value unit="lb">8184</Value>
                </EstimatedWeight>
            </FuelOnBoard>
            <MinimumFuelOnBoard>
                <Value unit="lb">4988</Value>
            </MinimumFuelOnBoard>
            <Function>TopOfClimb</Function>
        </Waypoint>
        <Waypoint waypointName="TOD" sequenceId="12">
            <Coordinates latitude="77730.0" longitude="-571230.0"/>
            <Airway>V15</Airway>
            <Altitude>
                <EstimatedAltitude>
                    <Value unit="ft/100">130</Value>
                </EstimatedAltitude>
            </Altitude>
            <MinimumSafeAltitude>
                <Value unit="ft/100">10</Value>
            </MinimumSafeAltitude>
            <SegmentWind>
               <Direction>
                   <Value unit="deg" type="true">238</Value>
               </Direction>
               <Speed>
                   <Value unit="kt">22</Value>
               </Speed>
            </SegmentWind>
            <SegmentWindComponent>
               <Value unit="kt">9</Value>
            </SegmentWindComponent>
            <SegmentShearRate>
                <SegmentVerticalWindChange>
                    <Value unit="kt">2</Value>
                </SegmentVerticalWindChange>
            </SegmentShearRate>
            <SegmentTemperature>
                <Value unit="C">2</Value>
            </SegmentTemperature>
            <SegmentISADeviation>
                <Value unit="C">13</Value>
            </SegmentISADeviation>
            <Tropopause>
                <Value unit="ft/100">520</Value>
            </Tropopause>
            <TrueAirSpeed>
                <EstimatedSpeed>
                    <Value unit="kt">340</Value>
                </EstimatedSpeed>
            </TrueAirSpeed>
            <MachNumber>
                <EstimatedMachNumber>
                    <Value>0.525</Value>
                </EstimatedMachNumber>
            </MachNumber>
            <IndicatedAirSpeed>
                <EstimatedSpeed>
                    <Value unit="kt">276</Value>
                </EstimatedSpeed>
            </IndicatedAirSpeed>
            <GroundSpeed>
                <EstimatedSpeed>
                    <Value unit="kt">349</Value>
                </EstimatedSpeed>
            </GroundSpeed>
            <Tracks>
                <OutboundTrack>
                    <Value unit="deg" type="true">121.4</Value>
                </OutboundTrack>
                <OutboundTrack>
                    <Value unit="deg" type="magnetic">111.9</Value>
                </OutboundTrack>
                <SegmentTrack>
                    <Value unit="deg" type="true">121.3</Value>
                </SegmentTrack>
                <SegmentTrack>
                    <Value unit="deg" type="magnetic">111.8</Value>
                </SegmentTrack>
            </Tracks>
            <GroundDistance>
                <Value unit="NM">15.2</Value>
            </GroundDistance>
            <RemainingGroundDistance>
                <Value unit="NM">47.3</Value>
            </RemainingGroundDistance>
            <AirDistance>
                <Value unit="NM">14.8</Value>
            </AirDistance>
            <RemainingAirDistance>
                <Value unit="NM">0046</Value>
            </RemainingAirDistance>
            <TimeFromPreviousWaypoint>
                <EstimatedTime>
                   <Value>PT00H03M</Value>
                </EstimatedTime>
            </TimeFromPreviousWaypoint>
            <TimeOverWaypoint>
                <EstimatedTime>
                    <Value>2025-01-08T20:18:00</Value>
                </EstimatedTime>
            </TimeOverWaypoint>
            <CumulatedFlightTime>
                <EstimatedTime>
                   <Value>PT00H09M</Value>
                </EstimatedTime>
            </CumulatedFlightTime>
            <RemainingFlightTime>
                <EstimatedTime>
                   <Value>PT00H11M</Value>
                </EstimatedTime>
            </RemainingFlightTime>
            <BurnOff>
                <EstimatedWeight>
                    <Value unit="lb">210</Value>
                </EstimatedWeight>
            </BurnOff>
            <CumulatedBurnOff>
                <EstimatedWeight>
                    <Value unit="lb">1326</Value>
                </EstimatedWeight>
            </CumulatedBurnOff>
            <FuelOnBoard>
                <EstimatedWeight>
                    <Value unit="lb">7974</Value>
                </EstimatedWeight>
            </FuelOnBoard>
            <MinimumFuelOnBoard>
                <Value unit="lb">4778</Value>
            </MinimumFuelOnBoard>
            <Function>TopOfDescent</Function>
        </Waypoint>
        <Waypoint waypointName="BOOKE" countryICAOCode="PH" waypointId="BOOKE" waypointLongName="BOOKE" sequenceId="13">
            <Coordinates latitude="77268.0" longitude="-570420.0"/>
            <Airway>V15</Airway>
            <MinimumSafeAltitude>
                <Value unit="ft/100">10</Value>
            </MinimumSafeAltitude>
            <SegmentWind>
               <Direction>
                   <Value unit="deg" type="true">236</Value>
               </Direction>
               <Speed>
                   <Value unit="kt">19</Value>
               </Speed>
            </SegmentWind>
            <SegmentWindComponent>
               <Value unit="kt">8</Value>
            </SegmentWindComponent>
            <SegmentShearRate>
                <SegmentVerticalWindChange>
                    <Value unit="kt">1</Value>
                </SegmentVerticalWindChange>
            </SegmentShearRate>
            <GroundSpeed>
                <EstimatedSpeed>
                    <Value unit="kt">354</Value>
                </EstimatedSpeed>
            </GroundSpeed>
            <Tracks>
                <OutboundTrack>
                    <Value unit="deg" type="true">121.4</Value>
                </OutboundTrack>
                <OutboundTrack>
                    <Value unit="deg" type="magnetic">111.9</Value>
                </OutboundTrack>
                <SegmentTrack>
                    <Value unit="deg" type="true">121.4</Value>
                </SegmentTrack>
                <SegmentTrack>
                    <Value unit="deg" type="magnetic">111.9</Value>
                </SegmentTrack>
                <InboundTrack>
                    <Value unit="deg" type="true">121.4</Value>
                </InboundTrack>
                <InboundTrack>
                    <Value unit="deg" type="magnetic">112.0</Value>
                </InboundTrack>
            </Tracks>
            <GroundDistance>
                <Value unit="NM">14.7</Value>
            </GroundDistance>
            <RemainingGroundDistance>
                <Value unit="NM">32.6</Value>
            </RemainingGroundDistance>
            <AirDistance>
                <Value unit="NM">15.8</Value>
            </AirDistance>
            <RemainingAirDistance>
                <Value unit="NM">0032</Value>
            </RemainingAirDistance>
            <TimeFromPreviousWaypoint>
                <EstimatedTime>
                   <Value>PT00H02M</Value>
                </EstimatedTime>
            </TimeFromPreviousWaypoint>
            <TimeOverWaypoint>
                <EstimatedTime>
                    <Value>2025-01-08T20:20:00</Value>
                </EstimatedTime>
            </TimeOverWaypoint>
            <CumulatedFlightTime>
                <EstimatedTime>
                   <Value>PT00H11M</Value>
                </EstimatedTime>
            </CumulatedFlightTime>
            <RemainingFlightTime>
                <EstimatedTime>
                   <Value>PT00H09M</Value>
                </EstimatedTime>
            </RemainingFlightTime>
            <BurnOff>
                <EstimatedWeight>
                    <Value unit="lb">59</Value>
                </EstimatedWeight>
            </BurnOff>
            <CumulatedBurnOff>
                <EstimatedWeight>
                    <Value unit="lb">1385</Value>
                </EstimatedWeight>
            </CumulatedBurnOff>
            <FuelOnBoard>
                <EstimatedWeight>
                    <Value unit="lb">7915</Value>
                </EstimatedWeight>
            </FuelOnBoard>
            <MinimumFuelOnBoard>
                <Value unit="lb">4719</Value>
            </MinimumFuelOnBoard>
            <Function>Enroute</Function>
        </Waypoint>
        <Waypoint waypointName="SHIGI" countryICAOCode="PH" waypointId="SHIGI" waypointLongName="SHIGI" sequenceId="14">
            <Coordinates latitude="76698.0" longitude="-569418.0"/>
            <Airway>V15</Airway>
            <MinimumSafeAltitude>
                <Value unit="ft/100">37</Value>
            </MinimumSafeAltitude>
            <SegmentWind>
               <Direction>
                   <Value unit="deg" type="true">226</Value>
               </Direction>
               <Speed>
                   <Value unit="kt">13</Value>
               </Speed>
            </SegmentWind>
            <SegmentWindComponent>
               <Value unit="kt">3</Value>
            </SegmentWindComponent>
            <SegmentShearRate>
                <SegmentVerticalWindChange>
                    <Value unit="kt">1</Value>
                </SegmentVerticalWindChange>
            </SegmentShearRate>
            <GroundSpeed>
                <EstimatedSpeed>
                    <Value unit="kt">281</Value>
                </EstimatedSpeed>
            </GroundSpeed>
            <Tracks>
                <OutboundTrack>
                    <Value unit="deg" type="true">89.1</Value>
                </OutboundTrack>
                <OutboundTrack>
                    <Value unit="deg" type="magnetic">79.6</Value>
                </OutboundTrack>
                <SegmentTrack>
                    <Value unit="deg" type="true">121.4</Value>
                </SegmentTrack>
                <SegmentTrack>
                    <Value unit="deg" type="magnetic">111.9</Value>
                </SegmentTrack>
                <InboundTrack>
                    <Value unit="deg" type="true">121.5</Value>
                </InboundTrack>
                <InboundTrack>
                    <Value unit="deg" type="magnetic">112.0</Value>
                </InboundTrack>
            </Tracks>
            <GroundDistance>
                <Value unit="NM">18.2</Value>
            </GroundDistance>
            <RemainingGroundDistance>
                <Value unit="NM">14.3</Value>
            </RemainingGroundDistance>
            <AirDistance>
                <Value unit="NM">18.5</Value>
            </AirDistance>
            <RemainingAirDistance>
                <Value unit="NM">0014</Value>
            </RemainingAirDistance>
            <TimeFromPreviousWaypoint>
                <EstimatedTime>
                   <Value>PT00H04M</Value>
                </EstimatedTime>
            </TimeFromPreviousWaypoint>
            <TimeOverWaypoint>
                <EstimatedTime>
                    <Value>2025-01-08T20:24:00</Value>
                </EstimatedTime>
            </TimeOverWaypoint>
            <CumulatedFlightTime>
                <EstimatedTime>
                   <Value>PT00H15M</Value>
                </EstimatedTime>
            </CumulatedFlightTime>
            <RemainingFlightTime>
                <EstimatedTime>
                   <Value>PT00H05M</Value>
                </EstimatedTime>
            </RemainingFlightTime>
            <BurnOff>
                <EstimatedWeight>
                    <Value unit="lb">98</Value>
                </EstimatedWeight>
            </BurnOff>
            <CumulatedBurnOff>
                <EstimatedWeight>
                    <Value unit="lb">1483</Value>
                </EstimatedWeight>
            </CumulatedBurnOff>
            <FuelOnBoard>
                <EstimatedWeight>
                    <Value unit="lb">7817</Value>
                </EstimatedWeight>
            </FuelOnBoard>
            <MinimumFuelOnBoard>
                <Value unit="lb">4621</Value>
            </MinimumFuelOnBoard>
            <Function>Enroute</Function>
        </Waypoint>
        <Waypoint waypointName="HNL" countryICAOCode="PH" waypointId="HNL" waypointLongName="HONOLULU" sequenceId="15">
            <Coordinates latitude="76710.0" longitude="-568548.0"/>
            <Airway>V15</Airway>
            <MinimumSafeAltitude>
                <Value unit="ft/100">32</Value>
            </MinimumSafeAltitude>
            <SegmentWind>
               <Direction>
                   <Value unit="deg" type="true">198</Value>
               </Direction>
               <Speed>
                   <Value unit="kt">11</Value>
               </Speed>
            </SegmentWind>
            <SegmentWindComponent>
               <Value unit="kt">3</Value>
            </SegmentWindComponent>
            <SegmentShearRate>
                <SegmentVerticalWindChange>
                    <Value unit="kt">1</Value>
                </SegmentVerticalWindChange>
            </SegmentShearRate>
            <GroundSpeed>
                <EstimatedSpeed>
                    <Value unit="kt">260</Value>
                </EstimatedSpeed>
            </GroundSpeed>
            <Tracks>
                <OutboundTrack>
                    <Value unit="deg" type="true">43.0</Value>
                </OutboundTrack>
                <OutboundTrack>
                    <Value unit="deg" type="magnetic">33.5</Value>
                </OutboundTrack>
                <SegmentTrack>
                    <Value unit="deg" type="true">89.1</Value>
                </SegmentTrack>
                <SegmentTrack>
                    <Value unit="deg" type="magnetic">79.6</Value>
                </SegmentTrack>
                <InboundTrack>
                    <Value unit="deg" type="true">89.2</Value>
                </InboundTrack>
                <InboundTrack>
                    <Value unit="deg" type="magnetic">79.7</Value>
                </InboundTrack>
            </Tracks>
            <GroundDistance>
                <Value unit="NM">13.5</Value>
            </GroundDistance>
            <RemainingGroundDistance>
                <Value unit="NM">0.8</Value>
            </RemainingGroundDistance>
            <AirDistance>
                <Value unit="NM">18.0</Value>
            </AirDistance>
            <RemainingAirDistance>
                <Value unit="NM">0001</Value>
            </RemainingAirDistance>
            <TimeFromPreviousWaypoint>
                <EstimatedTime>
                   <Value>PT00H04M</Value>
                </EstimatedTime>
            </TimeFromPreviousWaypoint>
            <TimeOverWaypoint>
                <EstimatedTime>
                    <Value>2025-01-08T20:29:00</Value>
                </EstimatedTime>
            </TimeOverWaypoint>
            <CumulatedFlightTime>
                <EstimatedTime>
                   <Value>PT00H19M</Value>
                </EstimatedTime>
            </CumulatedFlightTime>
            <RemainingFlightTime>
                <EstimatedTime>
                   <Value>PT00H01M</Value>
                </EstimatedTime>
            </RemainingFlightTime>
            <BurnOff>
                <EstimatedWeight>
                    <Value unit="lb">198</Value>
                </EstimatedWeight>
            </BurnOff>
            <CumulatedBurnOff>
                <EstimatedWeight>
                    <Value unit="lb">1681</Value>
                </EstimatedWeight>
            </CumulatedBurnOff>
            <FuelOnBoard>
                <EstimatedWeight>
                    <Value unit="lb">7619</Value>
                </EstimatedWeight>
            </FuelOnBoard>
            <MinimumFuelOnBoard>
                <Value unit="lb">4423</Value>
            </MinimumFuelOnBoard>
            <Remarks>
                <Remark remarkType="VOR frequency">
                    <Paragraph><Text>114.80</Text></Paragraph>
                </Remark>
            </Remarks>
            <Function>Vhf</Function>
        </Waypoint>
        <Waypoint waypointName="PHNL" countryICAOCode="PH" waypointId="PHNL" sequenceId="16">
            <Coordinates latitude="76746.0" longitude="-568512.0"/>
            <Airway>DCT</Airway>
            <SegmentWind>
               <Direction>
                   <Value unit="deg" type="true">193</Value>
               </Direction>
               <Speed>
                   <Value unit="kt">11</Value>
               </Speed>
            </SegmentWind>
            <SegmentWindComponent>
               <Value unit="kt">10</Value>
            </SegmentWindComponent>
            <SegmentShearRate>
                <SegmentVerticalWindChange>
                    <Value unit="kt">1</Value>
                </SegmentVerticalWindChange>
            </SegmentShearRate>
            <GroundSpeed>
                <EstimatedSpeed>
                    <Value unit="kt">266</Value>
                </EstimatedSpeed>
            </GroundSpeed>
            <Tracks>
                <OutboundTrack>
                    <Value unit="deg" type="true">43.0</Value>
                </OutboundTrack>
                <OutboundTrack>
                    <Value unit="deg" type="magnetic">33.5</Value>
                </OutboundTrack>
                <SegmentTrack>
                    <Value unit="deg" type="true">43.0</Value>
                </SegmentTrack>
                <SegmentTrack>
                    <Value unit="deg" type="magnetic">33.5</Value>
                </SegmentTrack>
                <InboundTrack>
                    <Value unit="deg" type="true">43.0</Value>
                </InboundTrack>
                <InboundTrack>
                    <Value unit="deg" type="magnetic">33.5</Value>
                </InboundTrack>
            </Tracks>
            <GroundDistance>
                <Value unit="NM">0.8</Value>
            </GroundDistance>
            <RemainingGroundDistance>
                <Value unit="NM">0.0</Value>
            </RemainingGroundDistance>
            <AirDistance>
                <Value unit="NM">1.1</Value>
            </AirDistance>
            <RemainingAirDistance>
                <Value unit="NM">0000</Value>
            </RemainingAirDistance>
            <TimeFromPreviousWaypoint>
                <EstimatedTime>
                   <Value>PT00H01M</Value>
                </EstimatedTime>
            </TimeFromPreviousWaypoint>
            <TimeOverWaypoint>
                <EstimatedTime>
                    <Value>2025-01-08T20:29:00</Value>
                </EstimatedTime>
            </TimeOverWaypoint>
            <CumulatedFlightTime>
                <EstimatedTime>
                   <Value>PT00H20M</Value>
                </EstimatedTime>
            </CumulatedFlightTime>
            <RemainingFlightTime>
                <EstimatedTime>
                   <Value>PT00H00M</Value>
                </EstimatedTime>
            </RemainingFlightTime>
            <BurnOff>
                <EstimatedWeight>
                    <Value unit="lb">13</Value>
                </EstimatedWeight>
            </BurnOff>
            <CumulatedBurnOff>
                <EstimatedWeight>
                    <Value unit="lb">1694</Value>
                </EstimatedWeight>
            </CumulatedBurnOff>
            <FuelOnBoard>
                <EstimatedWeight>
                    <Value unit="lb">7606</Value>
                </EstimatedWeight>
            </FuelOnBoard>
            <MinimumFuelOnBoard>
                <Value unit="lb">4410</Value>
            </MinimumFuelOnBoard>
            <Function>PrimaryArrivalAlternateAirport</Function>
        </Waypoint>
            </Waypoints>
            <Airport airportName="DANIEL K INOUYE INTL" airportFunction="PrimaryArrivalAlternateAirport">
                <AirportICAOCode>PHNL</AirportICAOCode>
                <AirportIATACode>HNL</AirportIATACode>
            </Airport>
            <RouteInformation fMSRouteName="PHLIPHNL">
                <AverageWindComponent>
                    <Value unit="kt">9</Value>
                </AverageWindComponent>
                <AverageTemperature>
                    <Value unit="C">2</Value>
                </AverageTemperature>
                <AverageISADeviation>
                    <Value unit="C">13</Value>
                </AverageISADeviation>
                <InitialAltitude>
                    <Value unit="ft/100">130</Value>
                </InitialAltitude>
                <RouteDescription>PHLI DCT LIH V15 HNL DCT PHNL</RouteDescription>
                <GroundDistance>
                    <Value unit="NM">91</Value>
                </GroundDistance>
                <AirDistance>
                    <Value unit="NM">88</Value>
                </AirDistance>
            </RouteInformation>
        </AlternateRoute>
    </AlternateRoutes>
    <AirportDataList>
        <AirportData>
            <Airport airportName="DANIEL K INOUYE INTL" airportFunction="DepartureAirport">
                <AirportICAOCode>PHNL</AirportICAOCode>
                <AirportIATACode>HNL</AirportIATACode>
            </Airport>
            <TerminalProcedure procedureType="SID">KEOLA3</TerminalProcedure>
        </AirportData>
        <AirportData>
            <Airport airportName="LIHUE" airportFunction="ArrivalAirport">
                <AirportICAOCode>PHLI</AirportICAOCode>
                <AirportIATACode>LIH</AirportIATACode>
            </Airport>
        </AirportData>
        <AirportData>
            <Airport airportName="DANIEL K INOUYE INTL" airportFunction="PrimaryArrivalAlternateAirport">
                <AirportICAOCode>PHNL</AirportICAOCode>
                <AirportIATACode>HNL</AirportIATACode>
            </Airport>
        </AirportData>
    </AirportDataList>
</FlightPlan>
